requests_resilient/__init__.py
requests_resilient/asynchronous.py
requests_resilient/errors.py
requests_resilient/synchronous.py
requests_resilient/utils.py
requests_resilient-0.2.0.dist-info/LICENSE
requests_resilient-0.2.0.dist-info/METADATA
requests_resilient-0.2.0.dist-info/WHEEL
requests_resilient-0.2.0.dist-info/top_level.txt
requests_resilient-0.2.0.dist-info/RECORD
