Metadata-Version: 2.1
Name: requests-resilient
Version: 0.2.0
Summary: A thin wrapper for requests adding resilience to network failures
Author-email: Leonardo Benitez <lsbenitezpereira@gmail.com>
License: MIT License
Project-URL: repository, https://github.com/LeonardoSanBenitez/requests_resilient
Project-URL: documentation, https://github.com/LeonardoSanBenitez/requests_resilient
Keywords: requests,resilience
Classifier: License :: OSI Approved :: MIT License
Classifier: Programming Language :: Python
Classifier: Programming Language :: Python :: 3
Requires-Python: >=3.7
License-File: LICENSE
Requires-Dist: requests >=2.31.0
Provides-Extra: build
Requires-Dist: build ; extra == 'build'
Requires-Dist: twine ; extra == 'build'
Provides-Extra: dev
Requires-Dist: python-dotenv ; extra == 'dev'
